gaufs/__init__.py
gaufs/data_generator.py
gaufs/gaufs.py
gaufs/genetic_search.py
gaufs/utils.py
gaufs/clustering_experiments/__init__.py
gaufs/clustering_experiments/base.py
gaufs/clustering_experiments/hierarchical.py
gaufs/clustering_experiments/kmeans.py
gaufs/evaluation_metrics/__init__.py
gaufs/evaluation_metrics/base.py
gaufs/evaluation_metrics/external.py
gaufs/evaluation_metrics/internal.py
gaufs/evaluation_metrics/utils.py
gaufs-1.1.2.dist-info/LICENCE
gaufs-1.1.2.dist-info/METADATA
gaufs-1.1.2.dist-info/NOTICE.txt
gaufs-1.1.2.dist-info/WHEEL
gaufs-1.1.2.dist-info/top_level.txt
gaufs-1.1.2.dist-info/RECORD
